runint/__init__.py
runint/benchmarks/base.py
runint/benchmarks/nlp/translation.py
runint/benchmarks/registry.py
runint/cli.py
runint/runtime/deploy/generators.py
runint/runtime/engines/__init__.py
runint/runtime/engines/base.py
runint/runtime/engines/ollama.py
runint/runtime/engines/vllm.py
runint/runtime/manager.py
runint/schemas/config.py
runint/schemas/results.py
runint-0.1.0.dist-info/METADATA
runint-0.1.0.dist-info/WHEEL
runint-0.1.0.dist-info/entry_points.txt
runint-0.1.0.dist-info/RECORD
